micromatrix/__init__.py
micromatrix/main.py
micromatrix-1.0.0.dist-info/LICENSE
micromatrix-1.0.0.dist-info/METADATA
micromatrix-1.0.0.dist-info/WHEEL
micromatrix-1.0.0.dist-info/RECORD
