Metadata-Version: 2.1
Name: micromatrix
Version: 1.0.0
Summary: A lightweight Python module which adds a generalized matrix class, supporting many matrix operations with no external dependencies
License: MIT
Keywords: python3,math,matrix
Author: h-janes
Author-email: dev@hjanes.com
Requires-Python: >=3.10,<4.0
Classifier: License :: OSI Approved :: MIT License
Classifier: Operating System :: OS Independent
Classifier: Programming Language :: Python :: 3
Classifier: Programming Language :: Python :: 3.10
Classifier: Programming Language :: Python :: 3.11
